{"trial_id": "0000", "hyperparameters": {"space": [{"class_name": "Choice", "config": {"name": "activation", "default": "relu", "conditions": [], "values": ["relu", "leaky_relu", "elu", "selu"], "ordered": false}}, {"class_name": "Int", "config": {"name": "n_hidden", "default": 2, "conditions": [], "min_value": 0, "max_value": 8, "step": 1, "sampling": "linear"}}, {"class_name": "Boolean", "config": {"name": "batch_norm", "default": false, "conditions": []}}, {"class_name": "Boolean", "config": {"name": "wide_and_deep", "default": false, "conditions": []}}, {"class_name": "Int", "config": {"name": "n_neurons0", "default": null, "conditions": [], "min_value": 16, "max_value": 256, "step": 1, "sampling": "linear"}}, {"class_name": "Int", "config": {"name": "n_neurons1", "default": null, "conditions": [], "min_value": 16, "max_value": 256, "step": 1, "sampling": "linear"}}], "values": {"activation": "elu", "n_hidden": 0, "batch_norm": false, "wide_and_deep": false, "n_neurons0": 230, "n_neurons1": 100, "tuner/epochs": 2, "tuner/initial_epoch": 0, "tuner/bracket": 6, "tuner/round": 0}}, "metrics": {"metrics": {"accuracy": {"direction": "max", "observations": [{"value": [0.42427271604537964], "step": 1}]}, "loss": {"direction": "min", "observations": [{"value": [1.3054273128509521], "step": 1}]}, "val_accuracy": {"direction": "max", "observations": [{"value": [0.6044999957084656], "step": 1}]}, "val_loss": {"direction": "min", "observations": [{"value": [1.2873862981796265], "step": 1}]}}}, "score": 0.6044999957084656, "best_step": 1, "status": "COMPLETED", "message": null}